skill_fallback_wolfram_alpha/LICENSE
skill_fallback_wolfram_alpha/LICENSE.md
skill_fallback_wolfram_alpha/README.md
skill_fallback_wolfram_alpha/__init__.py
skill_fallback_wolfram_alpha/skill.json
skill_fallback_wolfram_alpha/version.py
skill_fallback_wolfram_alpha/dialog/ca-es/email.body.dialog
skill_fallback_wolfram_alpha/dialog/ca-es/email.subject.dialog
skill_fallback_wolfram_alpha/dialog/ca-es/no.info.to.send.dialog
skill_fallback_wolfram_alpha/dialog/ca-es/not.understood.dialog
skill_fallback_wolfram_alpha/dialog/ca-es/sent.email.dialog
skill_fallback_wolfram_alpha/dialog/cs-cz/email.body.dialog
skill_fallback_wolfram_alpha/dialog/cs-cz/email.subject.dialog
skill_fallback_wolfram_alpha/dialog/cs-cz/no.info.to.send.dialog
skill_fallback_wolfram_alpha/dialog/cs-cz/not.understood.dialog
skill_fallback_wolfram_alpha/dialog/cs-cz/sent.email.dialog
skill_fallback_wolfram_alpha/dialog/da-dk/email.body.dialog
skill_fallback_wolfram_alpha/dialog/da-dk/email.subject.dialog
skill_fallback_wolfram_alpha/dialog/da-dk/no.info.to.send.dialog
skill_fallback_wolfram_alpha/dialog/da-dk/not.understood.dialog
skill_fallback_wolfram_alpha/dialog/da-dk/sent.email.dialog
skill_fallback_wolfram_alpha/dialog/de-de/email.body.dialog
skill_fallback_wolfram_alpha/dialog/de-de/email.subject.dialog
skill_fallback_wolfram_alpha/dialog/de-de/no.info.to.send.dialog
skill_fallback_wolfram_alpha/dialog/de-de/not.understood.dialog
skill_fallback_wolfram_alpha/dialog/de-de/sent.email.dialog
skill_fallback_wolfram_alpha/dialog/el-gr/email.body.dialog
skill_fallback_wolfram_alpha/dialog/el-gr/email.subject.dialog
skill_fallback_wolfram_alpha/dialog/el-gr/no.info.to.send.dialog
skill_fallback_wolfram_alpha/dialog/el-gr/not.understood.dialog
skill_fallback_wolfram_alpha/dialog/el-gr/sent.email.dialog
skill_fallback_wolfram_alpha/dialog/en-us/email.body.dialog
skill_fallback_wolfram_alpha/dialog/en-us/email.subject.dialog
skill_fallback_wolfram_alpha/dialog/en-us/no.email.dialog
skill_fallback_wolfram_alpha/neon_skill_fallback_wolfram_alpha.egg-info/PKG-INFO
skill_fallback_wolfram_alpha/neon_skill_fallback_wolfram_alpha.egg-info/SOURCES.txt
skill_fallback_wolfram_alpha/neon_skill_fallback_wolfram_alpha.egg-info/dependency_links.txt
skill_fallback_wolfram_alpha/neon_skill_fallback_wolfram_alpha.egg-info/entry_points.txt
skill_fallback_wolfram_alpha/neon_skill_fallback_wolfram_alpha.egg-info/requires.txt
skill_fallback_wolfram_alpha/neon_skill_fallback_wolfram_alpha.egg-info/top_level.txt
neon_skill_fallback_wolfram_alpha-3.0.0.dist-info/LICENSE
neon_skill_fallback_wolfram_alpha-3.0.0.dist-info/LICENSE.md
neon_skill_fallback_wolfram_alpha-3.0.0.dist-info/METADATA
neon_skill_fallback_wolfram_alpha-3.0.0.dist-info/WHEEL
neon_skill_fallback_wolfram_alpha-3.0.0.dist-info/entry_points.txt
neon_skill_fallback_wolfram_alpha-3.0.0.dist-info/top_level.txt
neon_skill_fallback_wolfram_alpha-3.0.0.dist-info/RECORD
