Metadata-Version: 2.1
Name: neon-skill-fallback-wolfram-alpha
Version: 3.0.0
Home-page: https://github.com/NeonGeckoCom/skill-fallback_wolfram_alpha
Author: Neongecko
Author-email: developers@neon.ai
License: BSD-3-Clause
License-File: LICENSE
License-File: LICENSE.md
Requires-Dist: requests>=2.13.0
Requires-Dist: neon-utils~=1.12
Requires-Dist: ovos-utils>=0.0.28,~=0.0
Requires-Dist: ovos-workshop>=0.0.15,~=0.0
